it_eng_python_logger_utils_dev_pypi/__init__.py
it_eng_python_logger_utils_dev_pypi/logger_utils.py
it_eng_python_logger_utils_dev_pypi-1.6.0.dist-info/METADATA
it_eng_python_logger_utils_dev_pypi-1.6.0.dist-info/WHEEL
it_eng_python_logger_utils_dev_pypi-1.6.0.dist-info/top_level.txt
it_eng_python_logger_utils_dev_pypi-1.6.0.dist-info/RECORD
