Metadata-Version: 2.1
Name: it-eng-python-logger-utils-dev-pypi
Version: 1.6.0
Summary: A logger util helper for Azure app insights and structured logging
Home-page: https://github.com/github/it-eng-packages/it_eng_python_logger_utils
Author: Dinnermonster
Author-email: it-engineering@github.com
Classifier: Programming Language :: Python :: 3.7
Classifier: License :: OSI Approved :: MIT License
Classifier: Operating System :: OS Independent
Requires-Python: >=3.7
Requires-Dist: opencensus-ext-requests
Requires-Dist: opencensus-ext-azure
Requires-Dist: requests
